reality_scan_mock/__init__.py
reality_scan_mock/main.py
realityscanmock-2025.8.22.1.dist-info/LICENSE
realityscanmock-2025.8.22.1.dist-info/METADATA
realityscanmock-2025.8.22.1.dist-info/WHEEL
realityscanmock-2025.8.22.1.dist-info/RECORD
